{
  "paragraphs": [
    {
      "text": "%md\n\n\u003cp\u003ethis is a test\u003c/p\u003e",
      "dateUpdated": "Jun 12, 2016 4:37:59 PM",
      "config": {
        "colWidth": 12.0,
        "graph": {
          "mode": "table",
          "height": 300.0,
          "optionOpen": false,
          "keys": [],
          "values": [],
          "groups": [],
          "scatter": {}
        },
        "enabled": true,
        "editorMode": "ace/mode/markdown"
      },
      "settings": {
        "params": {},
        "forms": {}
      },
      "jobName": "paragraph_1465767462083_-200583654",
      "id": "20160612-163742_942588569",
      "result": {
        "code": "SUCCESS",
        "type": "HTML",
        "msg": "\u003cp\u003ethis is a test\u003c/p\u003e\n"
      },
      "dateCreated": "Jun 12, 2016 4:37:42 PM",
      "dateStarted": "Jun 12, 2016 4:37:59 PM",
      "dateFinished": "Jun 12, 2016 4:37:59 PM",
      "status": "FINISHED",
      "progressUpdateIntervalMs": 500
    },
    {
      "config": {},
      "settings": {
        "params": {},
        "forms": {}
      },
      "jobName": "paragraph_1465767479054_1958273073",
      "id": "20160612-163759_1319911135",
      "dateCreated": "Jun 12, 2016 4:37:59 PM",
      "status": "READY",
      "progressUpdateIntervalMs": 500
    }
  ],
  "name": "Untitled Note 2",
  "id": "2BNX3RTNH",
  "angularObjects": {
    "2BQCH17EH:shared_process": [],
    "2BKYFDS7Q:shared_process": [],
    "2BN27KE9W:shared_process": [],
    "2BNR2S1SA:shared_process": [],
    "2BQSD9PWH:shared_process": [],
    "2BNX8S4PE:shared_process": [],
    "2BKYN4BSP:shared_process": [],
    "2BMGY8XB1:shared_process": [],
    "2BMJAS6GB:shared_process": [],
    "2BQ6M2APK:shared_process": [],
    "2BP8PS6E4:shared_process": [],
    "2BM8TNDU6:shared_process": [],
    "2BN3F679N:shared_process": [],
    "2BM19HA25:shared_process": [],
    "2BPTH31JC:shared_process": [],
    "2BPD56EQM:shared_process": [],
    "2BNSFTY5W:shared_process": [],
    "2BQ8KHB3A:shared_process": [],
    "2BQXFYNMJ:shared_process": []
  },
  "config": {},
  "info": {}
}